README.md
setup.cfg
setup.py
thinkific/__init__.py
thinkific/bundles.py
thinkific/chapters.py
thinkific/client.py
thinkific/contents.py
thinkific/coupons.py
thinkific/course_reviews.py
thinkific/courses.py
thinkific/enrollments.py
thinkific/orders.py
thinkific/products.py
thinkific/promotions.py
thinkific/users.py
thinkific/utils.py
thinkific/webhooks.py
thinkific.egg-info/PKG-INFO
thinkific.egg-info/SOURCES.txt
thinkific.egg-info/dependency_links.txt
thinkific.egg-info/requires.txt
thinkific.egg-info/top_level.txt