Metadata-Version: 2.1
Name: thinkific
Version: 0.1.1
Summary: Python Client wrapper for Thinkific API
Home-page: https://github.com/Prem-kumar27/thinkific-python
Author: Premkumar
Author-email: sprem1997@gmail.com
License: MIT
Download-URL: https://github.com/Prem-kumar27/thinkific-python/archive/refs/tags/v0.1.1.tar.gz
Keywords: thinkific,thinkific-api,thinkific-lms
Platform: UNKNOWN
Classifier: Development Status :: 3 - Alpha
Classifier: Intended Audience :: Developers
Classifier: License :: OSI Approved :: MIT License
Classifier: Operating System :: OS Independent
Classifier: Programming Language :: Python :: 3
Classifier: Programming Language :: Python :: 3.7
Classifier: Programming Language :: Python
